whendo_gpio/__init__.py
whendo_gpio/_version.py
whendo_gpio/action.py
whendo_gpio/imports.py
whendo_gpio/scheduler.py
whendo_gpio-0.0.1a6.dist-info/METADATA
whendo_gpio-0.0.1a6.dist-info/WHEEL
whendo_gpio-0.0.1a6.dist-info/top_level.txt
whendo_gpio-0.0.1a6.dist-info/RECORD
